{
    "BTC": "Bitcoin",
    "ETH": "Ethereum",
    "USDT": "Tether",
    "BNB": "BNB",
    "ADA": "Cardano",
    "XRP": "XRP",
    "SOL": "Solana",
    "DOT": "Polkadot",
    "DOGE": "Dogecoin",
    "USDC": "USD Coin",
    "LINK": "Chainlink",
    "LTC": "Litecoin",
    "BCH": "Bitcoin Cash",
    "AVAX": "Avalanche",
    "MATIC": "Polygon",
    "ICP": "Internet Computer",
    "VET": "VeChain",
    "FIL": "Filecoin",
    "TRX": "TRON",
    "EOS": "EOS",
    "XTZ": "Tezos",
    "XLM": "Stellar",
    "AAVE": "Aave",
    "ETC": "Ethereum Classic",
    "THETA": "Theta Network",
    "DAI": "Dai",
    "WLD": "Worldcoin",
    "XMR": "Monero",
    "UNI": "Uniswap",
    "BUSD": "Binance USD",
    "CELO": "Celo",
    "SAT": "Satoshi",
    "OP": "Optimism",
    "SHIB": "SHIBA Inu"
}